README
setup.py
pystk500v2/__init__.py
pystk500v2.egg-info/PKG-INFO
pystk500v2.egg-info/SOURCES.txt
pystk500v2.egg-info/dependency_links.txt
pystk500v2.egg-info/requires.txt
pystk500v2.egg-info/top_level.txt