Metadata-Version: 1.0
Name: pystk500v2
Version: 2.3.4
Summary: Python functions to parse and program AVR devices with the STK500V2 protocol.
Home-page: UNKNOWN
Author: David Ko
Author-email: david@barobo.com
License: GPL
Platform: UNKNOWN
